{
  "2026-03": {
    "month_str": "2026-03",
    "last_update": "2026-03-31T15:49:10",
    "phase": "月末总结阶段",
    "stats": {
      "total_count": 23,
      "total_distance": 226.8,
      "sports_count": {
        "Ride": 8,
        "Walk": 12,
        "Run": 3
      },
      "longest_ride_km": 32.53,
      "longest_run_km": 3.84,
      "hardest_session": {
        "date": "03-03",
        "type": "Run",
        "hr": 149,
        "zone": "乳酸阈值 (Z4)"
      },
      "favorite_time": "暮色",
      "avg_hr": {
        "Ride": "122bpm (稳态燃脂 (Z2))",
        "Walk": "102bpm (舒缓有氧 (Z1))",
        "Run": "140bpm (有氧强化 (Z3))"
      },
      "max_streak_days": 14
    },
    "ai_title": "破风稳态燃脂者",
    "ai_comment": "本月你破晓而行，运动次数和里程均大幅超越上月，最长连续运动14天展现出惊人毅力，平均心率稳定在稳态燃脂区间，03-03的Run更是冲破乳酸阈值，无氧极限潜力初现，暮色出没的运动习惯也颇为独特，期待下月继续突破！"
  }
}